df_notifications/__init__.py
df_notifications/admin.py
df_notifications/apps.py
df_notifications/channels.py
df_notifications/context_processors.py
df_notifications/decorators.py
df_notifications/defaults.py
df_notifications/fields.py
df_notifications/models.py
df_notifications/settings.py
df_notifications/tasks.py
df_notifications/drf/__init__.py
df_notifications/drf/serializers.py
df_notifications/drf/urls.py
df_notifications/drf/viewsets.py
df_notifications/migrations/0001_initial.py
df_notifications/migrations/0002_remove_notificationhistory_df_notifica_templat_fc63aa_idx_and_more.py
df_notifications/migrations/0003_remove_notificationhistory_df_notifica_templat_ec4b48_idx_and_more.py
df_notifications/migrations/0004_pushactioncategory_pushaction.py
df_notifications/migrations/0005_alter_pushactioncategory_options.py
df_notifications/migrations/0006_alter_userdevice_registration_id.py
df_notifications/migrations/0007_custompushmessage.py
df_notifications/migrations/0008_alter_custompushmessage_action_url_and_more.py
df_notifications/migrations/0009_alter_notificationhistory_instance_id.py
df_notifications/migrations/__init__.py
django_df_notifications-1.2.15.dist-info/LICENSE
django_df_notifications-1.2.15.dist-info/METADATA
django_df_notifications-1.2.15.dist-info/WHEEL
django_df_notifications-1.2.15.dist-info/top_level.txt
django_df_notifications-1.2.15.dist-info/RECORD
