Metadata-Version: 2.1
Name: django-df-notifications
Version: 1.2.15
Summary: Opinionated Django Omnichannel Notifications.
Author-email: Apexive OSS <open-source@apexive.com>
Project-URL: homepage, https://apexive.com/
Classifier: Environment :: Web Environment
Classifier: Framework :: Django
Classifier: Framework :: Django :: 3.2
Classifier: Framework :: Django :: 4.0
Classifier: Intended Audience :: Developers
Classifier: License :: OSI Approved :: MIT License
Classifier: Operating System :: OS Independent
Classifier: Programming Language :: Python
Classifier: Programming Language :: Python :: 3
Classifier: Programming Language :: Python :: 3 :: Only
Classifier: Programming Language :: Python :: 3.8
Classifier: Programming Language :: Python :: 3.9
Classifier: Topic :: Internet
Requires-Python: >=3.9
License-File: LICENSE
Requires-Dist: django
Requires-Dist: djangorestframework
Requires-Dist: django-df-api-drf >=1.0.4
Requires-Dist: firebase-admin
Requires-Dist: requests
Requires-Dist: django-slack
Requires-Dist: fcm-django >=1.0.15
Requires-Dist: celery
Requires-Dist: django-import-export
Requires-Dist: django-celery-beat
Requires-Dist: django-otp-twilio
Requires-Dist: Pillow
Provides-Extra: test
Requires-Dist: pytest ; extra == 'test'
Requires-Dist: pytest-django ; extra == 'test'
Requires-Dist: django-stubs[compatible-mypy] ; extra == 'test'
Requires-Dist: black ==23.7.0 ; extra == 'test'
Requires-Dist: ruff ==0.0.284 ; extra == 'test'
Requires-Dist: types-requests ; extra == 'test'
Requires-Dist: types-urllib3 ; extra == 'test'
Requires-Dist: django-dbtemplates ; extra == 'test'
Requires-Dist: pytest-cov ; extra == 'test'
Requires-Dist: pytest-mock ; extra == 'test'
Requires-Dist: pytest-celery ; extra == 'test'
